git_branch_sweeper/__init__.py
git_branch_sweeper/cli.py
git_branch_sweeper/git.py
git_branch_sweeper/process.py
git_branch_sweeper/styles.py
git_branch_sweeper/utils.py
git_branch_sweeper-1.1.0.dist-info/METADATA
git_branch_sweeper-1.1.0.dist-info/WHEEL
git_branch_sweeper-1.1.0.dist-info/entry_points.txt
git_branch_sweeper-1.1.0.dist-info/RECORD
