Metadata-Version: 2.1
Name: git-branch-sweeper
Version: 1.1.0
Summary: Interactive CLI tool to delete multiple local git branches at once.
Home-page: https://github.com/RenDelaCruz/git-branch-sweeper
Author: Ren Dela Cruz
Author-email: ren_delacruz@outlook.com
Requires-Python: >=3.10,<4.0
Classifier: Programming Language :: Python :: 3
Classifier: Programming Language :: Python :: 3.10
Classifier: Programming Language :: Python :: 3.11
Classifier: Programming Language :: Python :: 3.12
Requires-Dist: inquirerpy (>=0.3.4,<0.4.0)
Project-URL: Repository, https://github.com/RenDelaCruz/git-branch-sweeper
